{
    "Drop Watch: June 21st, 2024": {
        "title": "Drop Watch: June 21st, 2024",
        "score": 48,
        "url": "https://www.reddit.com/r/hiphopheads/comments/1dkuzc1/drop_watch_june_21st_2024/",
        "content": "#LPs\n\n- [**Peso Pluma - \u00c9XODO**](https://music.apple.com/us/album/%C3%A9xodo/1748015447) (w Quavo, Cardi B, Rich the Kid, Arc\u00e1ngel + more) **[Corridos, Latin Pop]**\n- [**G-Eazy - Freak Show**](https://open.spotify.com/album/3bBBR0YDmIcXnZlwfk9qSd) (w French Montana, Coi Leray, Leon Bridges, Burna Boy & Avonlea) **[Pop Rap, *RCA*]**\n- [**Kehlani - Crash**](https://music.apple.com/us/album/crash/1752190549) (w Jill Scott, Young Miko + more) **[R&B, *Atlantic*]**\n- [**Jowell & Randy (\ud83c\uddf5\ud83c\uddf7) - Viva La Musik**](https://open.spotify.com/album/1AFU8pGn801UpX69JsPLay) (w Rauw Alejandro, Wisin Y Yandel, De La Ghetto + more) **[Reggaet\u00f3n, *Rimas*]**\n- [**Big Yavo - The Giant**](https://open.spotify.com/album/3GPnpFxF7JRgDxPSlRHTGR) (w Hunxho, Yung Mal, BossMan Dlow, Peewee Longway + more) **[Trap]**\n- **[Ptazeta (\ud83c\uddea\ud83c\uddf8) - GORGONA](https://open.spotify.com/album/7Ae5Sye34ZPoRJiogQv7LD) [Spanish Rap, *Interscope*]**\n- [**Boosie Badazz - Happy Thanksgiving & Merry Christmas**](https://open.spotify.com/album/0gaCcfqJkkp3olRA4wEyYP) (w Rich Homie Quan, Hurricane Chris + more) **[Trap]**\n- **[Chavo - Lost For Words](https://open.spotify.com/album/3EQYXJM7ZzXIYbPryREYrQ) [Rap]**\n- [**Your Old Droog - Movie**](https://open.spotify.com/album/2C1iMGVsLhuj6odPjCn0kI) (w Method Man, Yasiin Bey, Denzel Curry, Madlib, Harry Fraud, Just Blaze, Conductor Williams + more) **[NY Rap]**\n- **[lou deezi - Bloody Tears](https://open.spotify.com/album/4CTX9H2dN24qgXdZp79zAR) [Bay Area Trap, *Thizzler*]**\n- [**Kaelin Ellis - You Are Here, Start.**](https://music.apple.com/us/album/you-are-here-start/1747803392) (w Saba, Kenny Mason, Buddy, Guapdad 4000, DUCKWRTH, TOBi & Anomalie + more) **[Producer, *Fool's Gold*]**\n- [**Leather Park & Odunsi (The Engine) - LEATHER PARK, VOL. 1**](https://open.spotify.com/album/714sz0U1nuTsGFbQiyMFfN) (w Cruel Santino, BYNX + more) **[Afropop, *EQT*]**\n- **[Kill Bill: The Rapper & Rav - KEEP THE CHANGE!](https://open.spotify.com/album/0DQBVmER87PWhDbtdTEiBY) [Horrorcore]**\n- **[Krayzie Bone - Chasing the Devil: Chapter 2 \"Salvation\"](https://open.spotify.com/album/7mopRAAvvKGhTGX37HTTkd) [Midwest Rap]**\n- **[AFN Peso - The Deluxe](https://open.spotify.com/album/3TVJ7K2HRgpAsdSnl72Btr) [Trap]**\n- [**CJ Fly & NasteeLuvzYou - the pharoah's return 2: Nubia**](https://open.spotify.com/album/5tOuEupTBIhK2T3AkNdbwc) (w Termanology, Ransom & Jamaar Milton) **[NY Rap]**\n- [**Da Beatminerz - Stifled Creativity**](https://open.spotify.com/album/35IMV2kpVJDmwOm9j47CK0) (w De La Soul, AZ, KRS-One, Pharaoh Monche, Smif-n-Wessun + more)  **[Rap]**\n- **[HOMEBOY SANDMAN - RICH II](https://music.apple.com/us/album/rich-ii/1751328816) [Rap]**\n- **[\u827e\u5fd7\u6052Asen - Life After Small Town](https://open.spotify.com/album/5YCrakqvO7BaesMX3Gytz1) [Rap]**\n- **[POLO PERKS <3 <3 <3, FearDorian & AyooLii - A Dogs Chance](https://open.spotify.com/album/6VTELlx0dtxxuKxAxD7fSy) [Internet Rap]**\n- **[Esham - Amuse Bouche](https://open.spotify.com/album/0DfZGzwKbmtEtziu2w1Dbr) [Horrorcore]**\n- [**Samuel Shabazz - PLANE BOY**](https://music.apple.com/us/album/plane-boy/1746836074) (w Babyface Ray + more) **[Michigan Trap]**\n- **[Menend (\ud83c\uddea\ud83c\uddf8) - SECUELAS](https://open.spotify.com/album/2B8wBzKyEJx0juVtjVebYu) [Spanish Rap]**\n- **[Maze Overlay & Observe Since 98 - Medium Raw](https://open.spotify.com/album/5di3INWqfP6lmW0YQ7M4kQ) [Rap]**\n- [**Tom G - Skroll Muzik, Vol. 11**](https://open.spotify.com/album/65Eu4H4eW2Q7fofvxXt47K) (w Sauce Walka + more) **[Rap]**\n- **[Pokelawls - MOVIE MUSIC](https://open.spotify.com/album/61fsTgiGo8vLIYIbuT9yDL) [Rap]**\n- [**Saint Jame$ - By Any Mean$**](https://open.spotify.com/album/2tk4ny8rvbKUTgZ5wfhqz1) (w Boldy James, Conway, Estee Nack, Rome Streetz + more) **[Rap]**\n- [**LOOK DAMIEN! - Hell of a Life**](https://open.spotify.com/album/20xiLeRraIuXxUEOpsyd0z) (w ANKHLEJOHN, Da$H, Fly Anakin, Quadie Diesel & Rahiem Supreme) **[Rap]**\n- [**Disko Boogie - StarzOnMarz 5**](https://open.spotify.com/album/0pXriDsYsnjXhDrLJXoDwP) (w Jason Martin, Zoe Osama, Kokane + more) **[West Coast Rap]**\n\n#Deluxe\n\n- [**Don Toliver - HARDSTONE PYSCHO**](https://store.dontolivermusic.com/) (w Lil Uzi Vert & Yeat) **[R&B]**\n- **[Tinashe - Match My Freak EP](https://open.spotify.com/album/1tDRvPJmMJhvYXbmVNMAXJ) [R&B]**\n- [**Wisin (\ud83c\uddf5\ud83c\uddf7) - Mr. W**](https://open.spotify.com/album/0uozDpPbY35wVv78dHMICs) (w De La Ghetto + more) **[Reggaet\u00f3n]**\n- **[Blockhead - The Aux Instrumentals](https://open.spotify.com/album/1Yn50kkCayBEXlOj6Vvc9l) [Beats, *Backwoodz*]**\n- **[Ol' Burger Beats (\ud83c\uddf3\ud83c\uddf4) - 74: Out of Time Instrumentals](https://open.spotify.com/album/4lpK72HDczHmlocoUUJMS4) [Beats, *Coalmine*]**\n- **[SURFACE GREY - Magnum Opus](https://open.spotify.com/album/2i5ghvee83Cr7lkjm7d0oO) [Rap]**\n\n#EPs\n\n- **[Maeta (\ud83c\uddfa\ud83c\uddf8) & KAYTRANADA (\ud83c\udde8\ud83c\udde6) - Endless Night](https://music.apple.com/us/album/endless-night/1750985604) [R&B, *Roc Nation*]**\n- **[C.R.O. (\ud83c\udde6\ud83c\uddf7) - Malos Cantores](https://open.spotify.com/album/2UWzZetnP0F9U2Q6sgEy6n) [Latin Rap, *DALE PLAY*]**\n- [**Berner & DRODi - 100 Sources of Income**](https://open.spotify.com/album/32njDpDhrDwWFWwfrTWari) (w Wiz Khalifa, Paul Wall, That Mexican OT + more) **[Rap]**\n- **[22Gz - Brooklyn\u2019s Most Wanted](https://open.spotify.com/album/1h4Vwt71rwTZe5KhXgrx5h) [BK Drill]**\n- **[Twit One (\ud83c\udde9\ud83c\uddea) - Crix](https://open.spotify.com/album/4hA4qHm6mGlJSqiKqetzmB) [Beats]**\n- **[Leo Waters - On Waters Ave](https://open.spotify.com/album/0nRN4Le9A5UMSeEo6kz5N6) [Rap]**\n- **[Willie Mac Jr & G.T. - Pay It Forward](https://open.spotify.com/album/01WD6wMiCUTmyNBKfsWbdV) [Trap]**\n- **[Raury - Southern Mystic](https://open.spotify.com/album/7alhsU5QHyVCM1OUcVHBCd) [Folk]**\n- **[Nyck Caution - Yellow Tape Road](https://open.spotify.com/album/2qd5Zcq5109TrPZHjQti2Y) [NY Rap]**\n- **[John Glacier (\ud83c\uddec\ud83c\udde7) - Duppy Gun](https://music.apple.com/us/album/duppy-gun-ep/1745722021) [UK Rap, *Young*]**\n- [**K Carbon - Diary of a Hustler**](https://open.spotify.com/album/1sp9Mw4UVCNCmqeVvAEuS7) (w GloRilla, BIG30, YTB Fatt, Gloss Up + more) **[Trap, *Choppa Gang Ent*]**\n- [**Shmurda61st - Long Live Shmurda**](https://open.spotify.com/album/7BYlYwQgay96KWD1yRNQlq) (w Smiley + more) **[Toronto Trap, *6ixbuzz*]**\n- **[Nef The Pharaoh - Welcome 2 Fatherhood](https://open.spotify.com/album/6jI6CZpe6OJaW6WCmOI6ET) [Bay Area Rap]**\n- **[cr1tter - yea I think](https://open.spotify.com/album/7GWCqTf8Uwfvkk2UluKBQE) [Rap]**\n- [**Lebra Jolie - What Was Said?**](https://open.spotify.com/album/789NgjZwh9qga5RsFoBsZ5) (w BIA, Saweetie & Skilla Baby) **[TX Trap, *Interscope*]**\n- **[Chester Watson & Elaquent - Montisona](https://open.spotify.com/album/65pf3Tn68V4Jv8aDg0hxWM) [Rap]**\n- **[RJ Payne - Hellraiser](https://open.spotify.com/album/4N1EkhVmys68Ao4jdT4QaJ) [Rap]**\n- [**Michael Christmas - Unsexy**](https://open.spotify.com/album/1knvs5Sqj3y4GRdWK39uiH) (w Chris Crack, FELIX!, Domo Genesis, Phiik & Lungs, Kipp Stone + more) **[Rap]**\n- **[Ben Carillo - Crecimiento, Demos Vol. II](https://open.spotify.com/album/1jhFxj9Y7Yxot7BX1634AE) [Latin]**\n- **[Nicotine - God's Baby](https://open.spotify.com/album/12OfGBC0O7VDmVeA5xwYng) [R&B]**\n- **[Goodbye Tomorrow - a\u1e67k o\u034en the block\u035a](https://open.spotify.com/album/1qOdq8Zb0lM9TLx0L0164t) [Rap]**\n- **[Tony Bontana (\ud83c\uddec\ud83c\udde7) - Trials & Tribulations of a Real Nigga](https://open.spotify.com/album/0M2r5Xuoy0zUpEGfgxvBkR) [Experimental Rap]**\n- [**Freshman Woes - A Tribe Called Fresh**](https://open.spotify.com/album/1JuEbsiVBBwW67LGeJnFp2) (w Fashawn, Myka 9, AJ Suede, Cashus King + more) **[Producer]**\n\n#Songs\n\n* Ariana Grande - the boy is mine (Remix) [feat. Monica & Brandy]\n* Rich The Kid - Gimme A Second (Remix) [feat. \u00a5$]\n* Jay Worthy & D\u0101M FunK - 105 West (feat. Ty Dolla $ign, Channel Tres, DJ Quik & A-Trak)\n* DJ Mustard - Parking Lot (feat. Travis Scott)\n* IDK & Turbo - TiFFANY (feat. Gunna)\n* Asake & Magicsticks - Wave (feat. Central Cee)\n* Kali Uchis & Josh Crocker - Never Be Yours\n* Niosmith - Take Me to the Edge (feat. Snoop Dogg)\n* Tyga & Yume - Uh Huh (feat. 310babii)\n* Ice Spice & RIOTUSA - Phatt Butt\n* Key Glock & King Wonka - Big Big Money\n* 6LACK - Fuck The Rap Game\n* GloRilla & Chaii Beats - TGIF\n* Villano Antillano & Young Martino - CamGirl >.< !!!\n* Aya Nakamura - 42\n* B-Lovee & Cash Cobain - All Alone\n* Fatboy SSE - Okay (Remix) [feat. Cash Cobain]\n* Headie One & Aitch - Tipsy\n* Tee Grizzley & Helluva - Robbery 7\n* Shoreline Mafia & Diego Ave - Work\n* The Alchemist - Seasons Change\n* Whethan & Flowdan - STEALTH BOMBER\n* $NOT & Cochise - HILARIOUS\n* Nemzzz & Zel - WYA\n* Van Buren Records - Doin Too Much\n* Jasiah & Waka Flocka Flame - Throw Em Out\n* Jaden - \"Roses\"\n* Snakeships & EARTHGANG -  Been A Minute (feat. Sinead Harnett)\n* EBK Jaaybo - Hotboiiz\n* EBK BCKDOE - House Game / Pick U 1\n* EBK Trey B - Put the Bity On\n* Knucks & Kare - Nkita (feat. Fimiguerrero)\n* MAVI & Angelo LeRoi - drunk prayer\n* Young Bull & 03 Greedo - We Ain't Trippin\n* Blanco - Ponzi Scheme\n* Amber Mark - Lovely Day\n* Chuck D - THE AMAZING WILLIE MAYS (Willie Mays Tribute)*\n* Boldy James & Conductor Williams - Offwhite Lumberjack\n* Juelz Santana & Jadakiss - Party N Bullshit \n* Baby Smoove - Jiffy\n* Hit-Boy & Don Cannon - SPILL*\n* LaRussell, Michael Sneed, P-LO, ClayDough & demahjiah - Big Dreams\n* Markell from the Circle - Soulful Song (feat. LaRussell)\n* Black Sherif - Kilos Milos\n* Mike Spiff & BIG30 - SPIN\n* Jay Exodus, Benny the Butcher, Jay Worthy & Chuck Inglish - Summer Activity\n* YT & Lancey Foux - Black & Tan\n* Coyote Jo Bastard & DD Osama - MAGIC\n* JPEGMAFIA - don't rely on other men (feat. Freaky)\n* The Streets - End of the Queue\n* Rakim, Kurupt & Masta Killa - BE ILL\n* Icewear Vezzo & Peezy - Aiight\n* Talibando - S680 (feat. Veeze)\n* THEY. - Diamonds and Pearls\n* FloFilz - Wisdom\n* BabyDrill - Dracula\n* JELEEL! - High Grade!\n* Summrs - nobody knows\n* Yuno Miles - Bad Boys (feat. BrBLuhTim)*\n* Sauce Walka & YTB Fatt - Where's My Soda?\n* Six Figga Trigga & Big Moochie Grape - Suitcase\n* M Slago - Heard Right (feat. Homeboy Sandman & Aesop Rock)\n* TiRon & Ayomari - Do What You Want (feat. Homeboy Sandman & Yummy Bingham)\n* Cookin Soul & Kid Frankie - Deals & Dreams\n* 1100 Himself - Shift Change (Remix) [feat. WESTSIDE BOOGIE]\n* RJmrLA - Whole Head (feat. Siete7x)\n* \u00d8DYSSEE & Saib - Wanderlust\n* Merkules - Ten Toes\n* Saucy Santana - Bizerk\n* TOBi & Kojey Radical - Ego Slide\n* \u00a3MONZO, Lamsi & Jme - S.I.T., Pt. 2\n* Baby Ghost - Laced (feat. RMC Mike)\n* Milc & Andy Savoie - Pendleton (feat. Fly Anakin)\n* Cootie - Lean Flow\n* Dizzy Michal - your fault (feat. YN Jay)\n* Fever 333 - New West Order\n* Draft Day - BUCUM\n* Daniel Payne - Rich Nigga Shit (feat. Chris Crack & Pablo Sanders) / Benz (feat. G Perico)\n* Big Shaq - Like Wot!\n* DB.Boutabag - Free Rio\n* MONTANA OF 300 - NOT LIKE US (REMIX)*\n* Jeshi - Total 90\n* Cousin Stizz - Wit Me or Not\n* Tae the Don, Lakayeh & Kash Doll - Get Rachet\n* DJ Harrison - BongoFeet / Hopppp\n* OMB Peezy - Time Heals and Hurts\n* DJ Muggs & RAZ FRESCO - The Eternal Now*\n* Tbi$h & Rv - STIX\n* Jay Prince - All I Need\n* Swifty Blue & Chito Rana$ - Ranchero Bravo\n* Big Sad 1900 & Baby Stone Gorillas - Crash Out\n* RP Boo & Armand Hammer \u2013 Blood Running High\n* Tre Loaded - Don't Panic\n* Jerome Thomas & Pitch 92 - Pull Up\n* Boondawg & Lelosa - ROLLING LOUD\n* LUCY (Cooper B. Handy) & SURF GANG - SAME THING\n* Frisco - Sorry Not Sorry\n* 1up Tee - Butt Naked / Click (feat. STAR BANDZ)\n* FCG Heem - What a Time To Be Alive\n* Mithril Oreder, Locksmith, C. Ray & eLZhi - Mamba\n* Planet Asia & Flying Lindus - All In\n* Akeem Ali - Old School Jams\n* Dide - Mental\n* Dave Blunts - The Cup\n* Starlito - Jenesis\n* Da$H - Blatant\n* Circa 97, Tha God Fahim & Giallo Point - Dump Gawd 97\n* John Wells & NVSV - Rubberbands\n* Doggystyleee - Soo Much Drama*\n* FLOHIO - Juice\n* Fuego Base & OT the Real - Arithmetic\n* iyes clark - shed your skin (feat. Ghais Guevara)\n* Mickey Factz, Tobes & C-Red - Fearless\n* Dheezy & Young Trav - Weird On Me (feat. EDS Collective, One Fifty & Rockness Monsta)\n* TrillDiego & Sparkheem - Dahmer / Dead Friends\n* NappyHIGH & Maggie Kiing - MiamiWithMyBitches\n* Shredgang Mone - Didn't Work\n* Deetranada - NEXT MOVE!\n* Nacho Picasso & TELEVANGEL - Do It For Johnny\n* OBIJUAN - Good Book\n* Big Ouee & DVNTBEATS - Different\n* Wing Vilma - Astro Cup (feat. Pink Navel)\n* Squadda B & Amarna - Will It Ever Get Better\n* HittaJ3 - Not Like Us (Remix)*\n* PirahnaP - Tit For Tat (Sada Baby Diss)*\n\n---\n\n##[Old Drop Watches](https://www.reddit.com/r/hiphopheads/search?q=%22drop+watch%22+-%22JQBX%22&restrict_sr=on&include_over_18=on&sort=new&t=all)\n\n##[2023](https://redd.it/101h66v) and [2024 Calendar](https://redd.it/18syxv7)",
        "num_comments": 39,
        "comments": [
            "Wow that's a dead week",
            "Puro Double P",
            "New rakim, kurupt and masta killa track\n\nJuelz Santana and jadakiss track\n\nKatori walker track",
            "Pokelawls? Lmao?",
            "Your Old Droog & Da Beatminerz albums getting heavy play this weekend",
            "Rj Payne has a new album called hellraiser",
            "\u201cKehlani with Jill Scott, Young Miko, *+ more*\u201d hahaha literally only Omah Lay in the *\u201d+ more\u201d* category",
            "gonna have to check out this new Chester Watson. used to listen to his stuff when he was first coming up but then it seem like he just disappeared",
            "Homeboy sandman now that's a guy i haven't heard in a long time...last time i heard him was on the LICE projects by aesop rock in 2017-18, he didn't really match aes lyrics and energy in most tracks tho(a few exceptions for sure). Is this new project any good and worth checking out?",
            "Spotify playlists updated. \n\nAlbums: https://open.spotify.com/playlist/0DnzOCj0ccuMbCqagPqXSv\n\nSingles: https://open.spotify.com/playlist/7nIjPEJ5BDTF21VaG5CGcI"
        ]
    },
    "Daily Discussion Thread 06/21/2024": {
        "title": "Daily Discussion Thread 06/21/2024",
        "score": 30,
        "url": "https://www.reddit.com/r/hiphopheads/comments/1dl4j5p/daily_discussion_thread_06212024/",
        "content": "# Welcome to the /r/hiphopheads daily discussion thread!\n\n### What's This Thread For?\n\n- Objective questions with right/wrong answers (_\"Does anyone know what is happening with Detox?\", \"What is the sample in C.R.E.A.M.?\", etc._) \n- General hip-hop discussion.\n- Meta posts, like mod feedback and ideas for the sub.\n\n### Thread Guidelines\n\n- Do not create a separate self-post for these types of discussions outside of this thread - if you do, **your post will be removed**, as stated in the [guidelines](http://www.reddit.com/r/hiphopheads/wiki/index).\n- Please be helpful and friendly.\n- If a question has been asked many times before, provide a link to a thread that contains the answer.\n\n### Recurring Discussions\n\n- [Top Ten Tuesday](https://www.reddit.com/r/hiphopheads/search/?q=author%3AHHHrobot+flair%3A%22top+ten%22&restrict_sr=on&sort=new&t=all)\n- [Billboard Chart Discussion](https://www.reddit.com/r/hiphopheads/search?q=author%3ARobYaLunch+title%3A%22Billboard+Chart+Discussion%22&restrict_sr=on&sort=new&t=all)\n- [Last.fm Thread: What Have You Been Listening To This Week?](https://www.reddit.com/r/hiphopheads/search?q=author%3AHHHrobot+flair%3ALast.fm&restrict_sr=on&sort=new&t=all)\n- [Drop Watch](https://www.reddit.com/r/hiphopheads/search?q=author%3ADropWatcher+title%3A%22Drop+Watch%22&restrict_sr=on&sort=new&t=all)\n- [Recommend If You Like Thread](https://www.reddit.com/r/hiphopheads/search/?q=author%3AHHHRobot+flair%3ARIYL&sort=new&restrict_sr=on&t=all)\n- [Listening Club](https://www.reddit.com/r/hiphopheads/search?q=author%3AHHHRobot+title%3A%22Listening+Club%22&restrict_sr=on&sort=new&t=all)\n\n### New to /r/hiphopheads or hip-hop in general?\n\nCheck out these lists if you don't know where to start. \n\n- [Essential Albums List](https://docs.google.com/spreadsheets/d/1ewEzXRHj8LGvUB3g9QbnIK_m89I2Q5Y2LzsgqKOG6Xg/)\n- [HHH Favourites List](https://docs.google.com/spreadsheets/d/1Qpbd-fHbMyfWXlWPRA_XfgzYayc8cIjn8J9CuL-aNpE/edit)\n\n_Please note that these lists are outdated and will be updated very soon._\n\n### Other Ways to Connect\n\n- [HipHopHeads RVRB Room](https://app.rvrb.one/channel/hhh) _(Spotify Premium required)_",
        "num_comments": 501,
        "comments": [
            "If you don't like hood politics I don't fuck wit you",
            "\u201cKeep makin' me dance, wavin' my hand and it won't be no threat\u201d\n\nKendrick loved \u201cHonestly Nevermind\u201d. Biggest win for Drake",
            "why would ice spice say \"got these bitches bitin' all my flows\" why did she pluralize that",
            "The internet has successfully bullied Game into explaining why he [wasn\u2019t allowed to pop out](https://www.complex.com/music/a/jadegomez510/the-game-addresses-absence-kendrick-lamar-pop-out-show)\n\n> Game also claims Top Dawg offered him partial ownership of TDE, but he declined. \n\n\ud83e\uddd0\ud83e\udd28\ud83e\udd14",
            "Kendrick Lamar music video being shot in Compton this weekend. Who wants to place bets on if it's Not Like Us MV or a new song?",
            "Hehe\u2026Drake has Kendrick right where he wants him. You see, while K.Dot was having his cute lil concert\u2026 Drake was studying the blade.\u00a0",
            "I do find it a little funny that there's a rapper who just picked the name Buddy.",
            "Someone said Big Fish Theory (Vince Staples) is Brat (Charlie XcX) for men",
            "As dope as a NLU video would be I hope this video shoot is for something else and is gonna be the start of his album roll out. I'm not complaining either way but I would like some non-diss track music.",
            "Tbh im glad Kendrick didnt overstack the bill with\nWest coast legacy acts. Kept it at Dre and kept it moving. The lineup was great because it really looked forward for LA\u2019s sound, keeping the spotlight on the new generation and the artists who are the new OGs."
        ]
    },
    "New XXXTentacion leaked voice memo contains audio saying that he had sexual relations with a 16yo Jocelyn Flores": {
        "title": "New XXXTentacion leaked voice memo contains audio saying that he had sexual relations with a 16yo Jocelyn Flores",
        "score": 731,
        "url": "https://www.youtube.com/watch?v=FvhUep6KNGM",
        "content": "",
        "num_comments": 600,
        "comments": [
            "Xxx doing something bad? With a woman? I am shocked.",
            "Yikes this is hard to hear. Took advantage of a young girl who he probably knew was suicidal and used her. Wtf bro",
            "She died when XXX was 19 btw",
            "I don\u2019t care what you think about age gaps. \n\nA well known manipulator and abuser used his popularity to fly out a 16 year old to his house for sex. \n\nFor me the issue isn\u2019t with the age difference but the obvious power dynamic. \n\nA 16 year old shouldn\u2019t be flying anywhere without supervision.. so irresponsible\n\nAre there situations where a 19 and 16 year old might not be weird? Possibly but there\u2019s no defending this piece of shit.",
            "Vic mensa was right",
            "It's well known that this guy was a piece of shit, people just decided to ignore it because he died after he made a sadboy album",
            "whole lotta super seniors in this subreddit revealing themselves",
            "Never understood why everyone idolized this piece of shit",
            "Who could have guessed that X was a bad guy",
            "This was known I thought"
        ]
    },
    "A$AP Rocky Announces 'Don't Be Dumb' for August 30th 2024": {
        "title": "A$AP Rocky Announces 'Don't Be Dumb' for August 30th 2024",
        "score": 2465,
        "url": "https://forms.sonymusicfans.com/campaign/asaprocky-dontbedumb/",
        "content": "",
        "num_comments": 200,
        "comments": [
            "I genuinely can\u2019t believe we made it bruh holy shit",
            "The producer lineup has some heat",
            "i genuinely thought he wouldn\u2019t drop again lmaoooo",
            "FINALLY. ONLY BEEN LIKE 6 YEARS. graduated from college & started my career in that time.",
            "Haven\u2019t really liked the singles he\u2019s dropped these past few years but love Testing.\n\n\nHere\u2019s hoping. Pumped that we\u2019re finally getting a new album at the least",
            "Bruh he been testing forever",
            "I USED TO PRAY FOR TIMES LIKE THIS",
            "Graduated high school college and started post grad in the time it took this mf to make a single album",
            "Jesus christ he edged this rollout -  i hope its good",
            "FUCKING FINALLY"
        ]
    },
    "Mac Lethal openly challenges Tom Macdonald to a battle on King of the Dot. $50k to charity for entry, loser pays additional $50k to charity.": {
        "title": "Mac Lethal openly challenges Tom Macdonald to a battle on King of the Dot. $50k to charity for entry, loser pays additional $50k to charity.",
        "score": 375,
        "url": "https://www.reddit.com/r/hiphopheads/comments/1dli7oh/mac_lethal_openly_challenges_tom_macdonald_to_a/",
        "content": "https://preview.redd.it/efxe5nbei08d1.png?width=458&format=png&auto=webp&s=eb0e3146ecfedf55cef69743b7656a8875bdf16b\n\n",
        "num_comments": 158,
        "comments": [
            "I just found out Tom MacDonald is Canadian. \n\nWhy is he doing the MAGA shit and waving the American flag? Is the Canadian right-wing just America larping? Is there no Canadian way of being a reactionary?",
            "Wow, truely a battle of a movable object vs a stoppable force",
            "I'm split between thinking Tom McDonald shouldn't be invited to KotD and thinking it would be funny for him to show up to a place where he's entirely unwelcome.",
            "Maybe we can fundraise 100k collectively for charity so these guys don\u2019t rap battle",
            "Maaaaan we do not care",
            "Tom McDonald has 50k?",
            "A failed battle rapper turned shitty YouTube rapper going up against a right-wing crackpot rapper will go down in the history books as the lamest rap battle since Canibus had to pull out his rhyme book",
            "They probably will host it too, they down bad rn",
            "White Boy Summer 2: Electric Boogaloo",
            "Mac Lethal and King of the Dot? What year is it?"
        ]
    }
}