{
    "Targeted shirts/mugs/onesies/whatever are now banned.": {
        "title": "Targeted shirts/mugs/onesies/whatever are now banned.",
        "score": 1752,
        "url": "https://www.reddit.com/r/oddlyspecific/comments/a81dj2/targeted_shirtsmugsonesieswhatever_are_now_banned/",
        "content": "Please do not submit them. /r/TargetedShirts is thataway.\n\nExample of what not to post:\n[Shirt](https://i.imgur.com/w9a7kud.jpg)",
        "num_comments": 35,
        "comments": [
            "[deleted]",
            "[deleted]",
            "[deleted]",
            "[removed]",
            "[removed]",
            "[removed]",
            "[removed]",
            "[removed]",
            "[removed]",
            "[removed]"
        ]
    },
    "Mushrooms": {
        "title": "Mushrooms",
        "score": 2153,
        "url": "https://i.redd.it/alblnqj3gd9d1.png",
        "content": "",
        "num_comments": 41,
        "comments": [
            "\"All mushrooms are edible.  Some only once.\"\n\nAn old proverb now attributed to Terry Pratchett",
            "You have 2/3s of a shot to see God then.",
            "\u201cBrian\u201d actually means \u201cExpendable\u201d in ancient Sumerian",
            "They probably observed the animals eating the good ones",
            "A week\u2019s unlikely unless you ate like, a basketful of them. Normal duration\u2019s 4-6 hours.",
            "These are the people I thank on thanksgiving. The people who literally died figuring out what we can eat.",
            "Supposedly, or so told me someone who knew someone who knew a shaman, that's the wrong order.  \nThe right order was, taking the magic mushroom, and let it tell you what all the other plants were for.  \nBut there most probably was lot of Brian & Co in the process.",
            "Which ones last a week? You know, so, uhhhhhhh... I can avoid them",
            "Weird, I know this guy!",
            "Norsemen on Netflix did a whole scene about this. \n\nThat show is brilliant"
        ]
    },
    "BUBBS, the fuck you doin\u2019?": {
        "title": "BUBBS, the fuck you doin\u2019?",
        "score": 842,
        "url": "https://i.redd.it/o79fj1tgx79d1.jpeg",
        "content": "",
        "num_comments": 66,
        "comments": [
            "That one legged stripper who only works on Fridays named Arrr-lene.",
            "Holy crap!  They have a no legged stripper and a three legged stripper at the same club?!",
            "maybe one of them has an unsexy leg",
            "You should see where she puts that artificial leg.",
            "When I was in my early 20s, my friends and I celebrated an event at a step club for laughs. We got one of our friends a lap dance from a stripper. She started by backing up toward him and when she whipped around, we noticed she had one arm. Stripping is for everyone.",
            "Certainly makes me want to check it out",
            "The worst part is that only one of the ladies has legs.",
            "Liquor and whooooores, liquor, and whores...",
            "That\u2019s just the way she goes\u2026",
            "There must be one without a leg."
        ]
    },
    "Come on, not Andy!": {
        "title": "Come on, not Andy!",
        "score": 802,
        "url": "https://i.redd.it/2rchdbuppc9d1.jpeg",
        "content": "",
        "num_comments": 42,
        "comments": [
            "I first read this as: assigned cop at birth",
            "Andy and Sheriff Truman crying right now",
            "All Children Are Bears? \ud83d\ude02",
            "Andy if you see this I'm coming",
            "You\u2019re the worst god damn one Andy",
            "Only the Sith deal in absolutes.... wait, DAMN IT!\n\nSeriously, though, it's fine to castigate the bad cops, but we have to remember to celebrate the good ones.",
            "Assigned car at birth ?",
            "\u201cSir, ma\u2019am, it\u2019s a cop\u2026\u201d",
            "No that's Andy from Samburg",
            "If that is Andy from Hamburg, Arkansas then your are definitely right"
        ]
    },
    "What? Why is this so specific?": {
        "title": "What? Why is this so specific?",
        "score": 122,
        "url": "https://i.redd.it/bgv0t4a38x8d1.jpeg",
        "content": "",
        "num_comments": 6,
        "comments": [
            "It's just ragging on 'fanon' that completely and utterly pisses on the established and canon traits of a character.",
            "Oh I thought it was spamton or something lol",
            "The joke is that it applies to literally nothing. It's hyper-specific on purpose.\n\nIt's ragging on these super annoying trends circling reddit. It feels like every week, somebody makes a meme template of:\n\n* Hey fandom, what does my favorite character say about me?\n* Hey fandom, what does my favorite arc say about me?\n* Hey fandom, which character is shown like this?\n* Hey fandom, which character is depicted as this but isn't this?\n* Hey fandom, fill in the blanks on this.\n\nShit like that. They then get spread to every single media-related subreddit, being low-effort engagement farms that seem to somehow keep getting thousands of upvotes consistently, and clogging up everyones feed. So the joke here is one of those templates, except it's useless and impossible to engage with.",
            "Cyrano de Bergerac ??",
            "Kirby"
        ]
    }
}