{
    "happy pride month, from r/wordington": {
        "title": "happy pride month, from r/wordington",
        "score": 3329,
        "url": "https://i.redd.it/hm3dfvhs234d1.jpeg",
        "content": "",
        "num_comments": 211,
        "comments": [
            "and a refreshing reminder that homophobia has no place in the subreddit whose main gimmick is gay black men lmao",
            "do you want us to like\n\nthug gayer\n\nwhat",
            "https://preview.redd.it/hd3ols3m434d1.png?width=720&format=pjpg&auto=webp&s=d98533860188bd6976bded535ae4fc956493f9a5",
            "(gay porn)\u00b2",
            "https://preview.redd.it/f4z3z3rl834d1.jpeg?width=1920&format=pjpg&auto=webp&s=dd2e9c0c79e046ce797fed6d6498bd270856581e",
            "https://preview.redd.it/196ufc56i34d1.jpeg?width=842&format=pjpg&auto=webp&s=f3bfe3497c32310afcb6b972cfbef7041d181f5f",
            "The woke mind virus done got my thuggers\ud83d\ude14\n\nhttps://preview.redd.it/l33pu5xx434d1.jpeg?width=1305&format=pjpg&auto=webp&s=072ed4406fddf904cd464a36d2efe3428366a4a6",
            "https://preview.redd.it/qjrnhvyc534d1.jpeg?width=1039&format=pjpg&auto=webp&s=947625012464a20a8f22032e33aaa76bb45bfbf1",
            "We are now even more gay\n\nhttps://preview.redd.it/73hzb4zw734d1.jpeg?width=1080&format=pjpg&auto=webp&s=f6c80c91817f94d5ab226519f1c1068d60178487\n\nAwesome",
            "https://i.redd.it/vibbj3ahk34d1.gif"
        ]
    },
    "About the recent increase in racist comments in wordington ": {
        "title": "About the recent increase in racist comments in wordington ",
        "score": 1021,
        "url": "https://www.reddit.com/r/wordington/comments/1dqjhmj/about_the_recent_increase_in_racist_comments_in/",
        "content": "***You are not funny, doesn't belong in wordington***\n\nWordington is not a place for hate, your comment will be removed and if you are a repeat offender you will catch a ban\n\n***Please report***\nIf anyone comes across any form of hate please report so that we get a notification ",
        "num_comments": 120,
        "comments": [
            "https://i.redd.it/13ml7oiqlb9d1.gif",
            "Wordington mod",
            "Thugphobia? On my gay black porn sub?????\n\nhttps://preview.redd.it/kaw6141wsb9d1.png?width=2139&format=pjpg&auto=webp&s=2b80090ec3c211776c2d8d874f1d113a6d4fac67",
            "This is 7/11 of Wordington\n\nWhat's next? Banning homophobia on my gay black porn subredit? Next thing you know they ban you from fighting over food or being naked in front of your kids. \n\nThis is the darkest timeline. \n\nWordington has FALLEN! 1!!",
            "https://preview.redd.it/qfathyhunb9d1.png?width=1025&format=pjpg&auto=webp&s=8a0127700782a09c1bc84628120a5f302fd53367",
            "https://i.redd.it/d164nhdgwb9d1.gif",
            "wordington 1984",
            "Thugphobia is over!!!\n\nhttps://preview.redd.it/jq9moao8fb9d1.jpeg?width=640&format=pjpg&auto=webp&s=d51623355ce9070b728359535c5bf9053ae34339",
            "The Proletariat masses of Wordington must *cum* together to defeat the bourgeoisie thugaphobes! For the glory of M.I.L.F!\n\n*Men in leggings fucking*",
            "All instances of Thugphobia will be met with violent force"
        ]
    },
    "wordington insult": {
        "title": "wordington insult",
        "score": 95,
        "url": "https://v.redd.it/eftu9jpaff9d1",
        "content": "",
        "num_comments": 15,
        "comments": [
            "To download the video you can use one of the following sites:\n\n* [RedditSave](https://redditsave.com/info?url=https://www.reddit.com/r/wordington/comments/1dr1hus/wordington_insult/)\n* [SaveMP4](https://savemp4.red/?url=https://www.reddit.com/r/wordington/comments/1dr1hus/wordington_insult/)\n* [RedditVideoDL](https://redditvideodl.com/dl.php?url=https://www.reddit.com/r/wordington/comments/1dr1hus/wordington_insult/)\n* [SaveRedd.it](https://saveredd.it/?url=https://www.reddit.com/r/wordington/comments/1dr1hus/wordington_insult/) (click on the Download button below Search Video)\n\n\n*I am a bot, and this action was performed automatically. Please [contact the moderators of this subreddit](/message/compose/?to=/r/wordington) if you have any questions or concerns.*",
            "What happens when your kid is chronically online",
            "ALL THESE THINGS YOU SAID ALL THE THINGS YOU SAID RUNNING THROUGH MY HEAD RUNNING THROUGH MY HEAD RUNNING THROUGH MY HEAD",
            "Not his ass talkin\n\nhttps://preview.redd.it/3lyuurepmg9d1.jpeg?width=623&format=pjpg&auto=webp&s=fc9575230cc5cef56c0cd22587a49f940fb5a3a0",
            "Educated dedicated vaccinated \ud83d\udc4d",
            "What\u2019s he\u2019s saying I\u2019m currently at a party where I can barely hear my own voice",
            "Thr laughing in the background lmao",
            "God I thought he was saying cunt, I didn\u2019t hear chud until I read the comments. Bros cooked",
            "Holy Reddit, this guy is as mad as Evil Keanu Reeves!",
            "Xer voice is so beautiful"
        ]
    },
    "Wordington politics": {
        "title": "Wordington politics",
        "score": 208,
        "url": "https://i.redd.it/q1d1rgwxnd9d1.jpeg",
        "content": "",
        "num_comments": 10,
        "comments": [
            "https://preview.redd.it/rhksxvq63e9d1.jpeg?width=1170&format=pjpg&auto=webp&s=4b57e38c7b74177f91688808ed1b726123586d79",
            "Gay\u2705black\u274cMen\u2753\n\nWordington what the thug",
            "I love this person",
            "PLAP PLAP PLAP  I'm too lazy to think of the imperative segment",
            "Losercity crossover episode",
            "sauce rn",
            "https://preview.redd.it/nqgbtxu3bf9d1.jpeg?width=750&format=pjpg&auto=webp&s=7da8a0082cb2248278ea27f1895d670c9090caf6",
            "https://e621.net/posts/2395809?q=republican_elephant",
            "I don't have it",
            "Opposing horse"
        ]
    },
    "thugphobic w*men": {
        "title": "thugphobic w*men",
        "score": 356,
        "url": "https://v.redd.it/5mf1dtz4qc9d1",
        "content": "",
        "num_comments": 44,
        "comments": [
            "To download the video you can use one of the following sites:\n\n* [RedditSave](https://redditsave.com/info?url=https://www.reddit.com/r/wordington/comments/1dqpwwq/thugphobic_wmen/)\n* [SaveMP4](https://savemp4.red/?url=https://www.reddit.com/r/wordington/comments/1dqpwwq/thugphobic_wmen/)\n* [RedditVideoDL](https://redditvideodl.com/dl.php?url=https://www.reddit.com/r/wordington/comments/1dqpwwq/thugphobic_wmen/)\n* [SaveRedd.it](https://saveredd.it/?url=https://www.reddit.com/r/wordington/comments/1dqpwwq/thugphobic_wmen/) (click on the Download button below Search Video)\n\n\n*I am a bot, and this action was performed automatically. Please [contact the moderators of this subreddit](/message/compose/?to=/r/wordington) if you have any questions or concerns.*",
            "we need a thug rehabilition program for former husbands",
            "This is why we fuck men",
            "Conclusion: this man needs a thug to hold him tight, whisper sweet things in his ear, etc",
            "/unthug I just tried it to see if it works, neither of them do the hotline, for the husband one it says \u201cthey need to be heard and this is his way of taking back control???\u201d \n\nThe second resource is the national domestic abuse support thing for both. Why tf isn\u2019t it first??",
            "Dude I just looked it up. Thats true. Thats like 100%, everything he said was true.\n\nhttps://preview.redd.it/0i1yea4h5e9d1.jpeg?width=639&format=pjpg&auto=webp&s=69a4fb43a9307c9faca736933fad649bd354230b",
            "Wouldn\u2019t life be so much easier if everyone had a government mandated thug boyfriend to love and cherish every day?",
            "just need to thug it out",
            "https://preview.redd.it/xnd8k8tprg9d1.jpeg?width=1170&format=pjpg&auto=webp&s=71308a226cc1e460a18a3540f110959a44f4358d\n\nSTFU I DONT CARE ABOUT THIS STUPID GENDER WAR RAGE BAIT POST THUGS GOD DAMN IT",
            "/unthug for a sec not attacking the point but can we not post right wing reactionaries? don\u2019t want this sub to suffer the fate of r slash shitposting"
        ]
    }
}